shura/__init__.py
shura/logger.py
shura-0.2.0.dist-info/METADATA
shura-0.2.0.dist-info/WHEEL
shura-0.2.0.dist-info/top_level.txt
shura-0.2.0.dist-info/RECORD
