Metadata-Version: 2.4
Name: shura
Version: 0.2.0
Summary: Elegant, colored, plug-and-play logging for Python
Home-page: https://github.com/guy-shaul/shura
Author: Guy Shaul
Author-email: guyshaul8@gmail.com
Classifier: Programming Language :: Python :: 3
Classifier: License :: OSI Approved :: MIT License
Classifier: Operating System :: OS Independent
Requires-Python: >=3.6
Requires-Dist: colorama
Dynamic: author
Dynamic: author-email
Dynamic: classifier
Dynamic: home-page
Dynamic: requires-dist
Dynamic: requires-python
Dynamic: summary
